Metadata-Version: 2.1
Name: qwertypy
Version: 1.0.0
Summary: My personal python utilities library.
Home-page: https://qwertyvipul.io/qwertypy/
Author: Vipul Sharma | @qwertyvipul
Project-URL: Repository, https://github.com/qwertyvipul/qwertypy
Project-URL: Changelog, https://github.com/qwertyvipul/qwertypy/blob/main/CHANGELOG.md
Project-URL: Colab notebook, https://colab.research.google.com/drive/1SK96YfBgIPY-CKNfvQxvBKkJnNA7fSCe?usp=sharing
Classifier: Programming Language :: Python :: 3
Classifier: License :: OSI Approved :: MIT License
Classifier: Operating System :: OS Independent
Requires-Python: >=3.6
License-File: LICENSE
